Metadata-Version: 2.1
Name: s3resumable
Version: 0.0.2
Summary: Resumable S3 download
Home-page: https://github.com/immfly/s3resumable
Author: Immfly
Author-email: infra-team+pypi@immfly.com
License: UNKNOWN
Platform: UNKNOWN
Classifier: Programming Language :: Python :: 2
Classifier: Programming Language :: Python :: 2.7
Classifier: Programming Language :: Python :: 3
Classifier: Programming Language :: Python :: 3.7
Classifier: Topic :: Internet
Classifier: Topic :: Software Development :: Libraries
Classifier: Operating System :: OS Independent
Classifier: License :: OSI Approved :: Apache Software License
Requires-Python: >=2.6
Provides-Extra: dev
